LICENSE
README.md
pyproject.toml
setup.py
tleng.egg-info/PKG-INFO
tleng.egg-info/SOURCES.txt
tleng.egg-info/dependency_links.txt
tleng.egg-info/requires.txt
tleng.egg-info/top_level.txt
tleng2/__init__.py
tleng2/__main__.py
tleng2/components/__init__.py
tleng2/components/camera.py
tleng2/components/map.py
tleng2/components/renderable.py
tleng2/components/scene.py
tleng2/ecs/__init__.py
tleng2/ecs/component.py
tleng2/ecs/entity.py
tleng2/ecs/system.py
tleng2/engine/__init__.py
tleng2/engine/event_bus.py
tleng2/engine/game.py
tleng2/engine/listener.py
tleng2/engine/methods.py
tleng2/engine/properties.py
tleng2/engine/renderer.py
tleng2/engine/scene_manager.py
tleng2/engine/settings.py
tleng2/engine/ui_manager.py
tleng2/object/__init__.py
tleng2/object/area.py
tleng2/object/point.py
tleng2/object/sprite.py
tleng2/physics/__init__.py
tleng2/physics/object.py
tleng2/physics/projectile.py
tleng2/services/__init__.py
tleng2/services/animation.py
tleng2/services/cache.py
tleng2/services/data_structure.py
tleng2/services/font.py
tleng2/services/image.py
tleng2/services/sound.py
tleng2/services/sprite_stack.py
tleng2/services/tilemap.py
tleng2/systems/__init__.py
tleng2/systems/movement.py
tleng2/ui_elements/__init__.py
tleng2/ui_elements/arrow.py
tleng2/ui_elements/button.py
tleng2/ui_elements/label.py
tleng2/ui_elements/slider.py
tleng2/ui_elements/switch.py
tleng2/utils/__init__.py
tleng2/utils/annotations.py
tleng2/utils/colors.py
tleng2/utils/debug.py
tleng2/utils/utils.py
tleng2/utils/subpixel/__init__.py
tleng2/utils/subpixel/subpixelsurface.py
tleng2/utils/subpixel/testsubpixelbitmap.py