Metadata-Version: 2.1
Name: tleng
Version: 2.2.0.dev11
Summary: TLeng is a python 2d game engine
Author: Theolaos
Project-URL: Homepage, https://github.com/tl-ecosystem/tleng
Project-URL: Issues, https://github.com/tl-ecosystem/tleng/issues
Classifier: Programming Language :: Python :: 3
Classifier: License :: OSI Approved :: MIT License
Classifier: Operating System :: OS Independent
Requires-Python: >=3.11
License-File: LICENSE
